tox_extras.py
tox_extras-0.0.2.dist-info/LICENSE.txt
tox_extras-0.0.2.dist-info/METADATA
tox_extras-0.0.2.dist-info/WHEEL
tox_extras-0.0.2.dist-info/entry_points.txt
tox_extras-0.0.2.dist-info/top_level.txt
tox_extras-0.0.2.dist-info/RECORD
