Metadata-Version: 2.1
Name: tox-extras
Version: 0.0.2
Summary: A tox plugin to install extras directly into a testenv
Author-email: Thomas Gilgenast <thomasgilgenast@gmail.com>
Project-URL: repository, https://github.com/sclabs/tox-extras
Requires-Python: >=3.7
License-File: LICENSE.txt
Requires-Dist: tomli
Requires-Dist: tox >=4
Provides-Extra: dev
Requires-Dist: tox-extras[lint,test,type] ; extra == 'dev'
Provides-Extra: lint
Requires-Dist: black ==23.3.0 ; extra == 'lint'
Requires-Dist: ruff ==0.0.262 ; extra == 'lint'
Provides-Extra: test
Requires-Dist: pytest ==7.3.1 ; extra == 'test'
Requires-Dist: tox ==4.4.12 ; extra == 'test'
Provides-Extra: type
Requires-Dist: mypy ==1.2.0 ; extra == 'type'
